strs/__init__.py
strs/__main__.py
strs/commands/__init__.py
strs/commands/more.py
strs/commands/string/__init__.py
strs/commands/string/analyze.py
strs/commands/string/transform.py
strs/commands/string/validate.py
strs/core/__init__.py
strs/core/base.py
strs/core/constants.py
strs/core/decorators.py
strs/core/input.py
strs/core/process.py
strs/core/types.py
strs/plugins/__init__.py
strs/plugins/default.py
tests/__init__.py
strs-0.4.2.dist-info/LICENSE
strs-0.4.2.dist-info/METADATA
strs-0.4.2.dist-info/WHEEL
strs-0.4.2.dist-info/entry_points.txt
strs-0.4.2.dist-info/top_level.txt
strs-0.4.2.dist-info/RECORD
