Metadata-Version: 2.1
Name: strs
Version: 0.4.2
Summary: Easy string tools for the shell
Home-page: https://github.com/alexdelorenzo/strs
Author: Alex DeLorenzo (alexdelorenzo.dev)
License: AGPL 3.0
Requires-Python: >=3.10
License-File: LICENSE
Requires-Dist: emoji <1.7.0,>=1.6.1
Requires-Dist: fire <0.5.0,>=0.4.0
Requires-Dist: more-itertools <8.13.0,>=8.12.0
Requires-Dist: StrEnum <0.5.0,>=0.4.7
Requires-Dist: Unidecode <1.4.0,>=1.3.2
Requires-Dist: unpackable <0.1.0,>=0.0.4
